[
  {
    "task_id": 1,
    "workflow_id": "workflow-v1",
    "status": "COMPLETED",
    "current_step": "final-review",
    "steps": [
      {
        "step_id": "requirement-clarification",
        "name": "需求澄清",
        "status": "COMPLETED",
        "started_at": "2026-03-17T07:03:51.577170",
        "completed_at": "2026-03-17T07:03:51.577170",
        "retry_count": 0,
        "error": null
      },
      {
        "step_id": "solution-design",
        "name": "方案设计",
        "status": "COMPLETED",
        "started_at": "2026-03-17T07:03:51.577170",
        "completed_at": "2026-03-17T07:03:51.577170",
        "retry_count": 0,
        "error": null
      },
      {
        "step_id": "development-implementation",
        "name": "开发实现",
        "status": "COMPLETED",
        "started_at": "2026-03-17T07:03:51.577170",
        "completed_at": "2026-03-17T07:03:51.577170",
        "retry_count": 0,
        "error": null
      },
      {
        "step_id": "qa-validation",
        "name": "测试验证",
        "status": "COMPLETED",
        "started_at": "2026-03-17T07:03:51.577170",
        "completed_at": "2026-03-17T07:03:51.577170",
        "retry_count": 0,
        "error": null
      },
      {
        "step_id": "final-review",
        "name": "结果评审",
        "status": "COMPLETED",
        "started_at": "2026-03-17T07:03:51.577170",
        "completed_at": "2026-03-17T07:03:51.577170",
        "retry_count": 0,
        "error": null
      }
    ],
    "worktree_path": "/tmp/mock-worktree",
    "branch": "task/1",
    "context": {
      "reviewReportPath": "docs/review.md",
      "approved": true,
      "comments": "[Mock] Code looks good. All tests pass. Approved."
    },
    "id": 1,
    "created_at": "2026-03-17T07:03:51.577170",
    "updated_at": "2026-03-17T07:03:51.577170"
  }
]
